README.txt
setup.py
pomelo/__init__.py
pomelo/amq_util.py
pomelo/coming.py
pomelo/es_util.py
pomelo/hoster.py
pomelo/ppt_util.py
pomelo/s3_util.py
pomelo/timehlp.py
pomelo/zk_util.py
pomelo.egg-info/PKG-INFO
pomelo.egg-info/SOURCES.txt
pomelo.egg-info/dependency_links.txt
pomelo.egg-info/requires.txt
pomelo.egg-info/top_level.txt
pomelo.egg-info/zip-safe