Metadata-Version: 1.1
Name: pomelo
Version: 0.1.4
Summary: get hoster info or thread etc.
Home-page: https://pypi.python.org/pypi/pomelo
Author: Andrew liu
Author-email: 1185978974@qq.com
License: GPL
Keywords: ssh python python3
Platform: UNKNOWN
Classifier: License :: OSI Approved :: MIT License
Classifier: Programming Language :: Python
Classifier: Intended Audience :: Developers
Classifier: Operating System :: OS Independent
